lpfgopt/VERSION
lpfgopt/__init__.py
lpfgopt/c_leapfrog.py
lpfgopt/leapfrog.py
lpfgopt/leapfrog_c.dll
lpfgopt/opt_result.py
lpfgopt/scipy_min.py
lpfgopt-1.0.1.dist-info/LICENCE.txt
lpfgopt-1.0.1.dist-info/METADATA
lpfgopt-1.0.1.dist-info/WHEEL
lpfgopt-1.0.1.dist-info/top_level.txt
lpfgopt-1.0.1.dist-info/RECORD
