Metadata-Version: 2.1
Name: lpfgopt
Version: 1.0.1
Summary: Leap Frog Optimizer
Home-page: http://www.r3eda.com/
Author: Mark E. Redd
Author-email: redddogjr@gmail.com
License: MIT
Download-URL: https://github.com/flythereddflagg/lpfgopt
Keywords: optimization direct-search gradient-free
Platform: UNKNOWN
Classifier: Development Status :: 5 - Production/Stable
Classifier: Intended Audience :: Science/Research
Classifier: Intended Audience :: Manufacturing
Classifier: Intended Audience :: Education
Classifier: Intended Audience :: End Users/Desktop
Classifier: License :: OSI Approved :: MIT License
Requires-Python: >=3.6
